exemple_package/__init__.py
exemple_package/calculus.py
exemple_package/demulus.py
examplePackageBieroElCorridor-0.0.1.dist-info/LICENSE
examplePackageBieroElCorridor-0.0.1.dist-info/METADATA
examplePackageBieroElCorridor-0.0.1.dist-info/WHEEL
examplePackageBieroElCorridor-0.0.1.dist-info/top_level.txt
examplePackageBieroElCorridor-0.0.1.dist-info/RECORD
